{
  "id": 1,
  "robots": [
    {
      "id": "r2",
      "name": "R2"
    },
    {
      "id": "r3",
      "name": "R3"
    }
  ],
  "startingBaskets": [
    "magenta",
    "blue"
  ],
  "isTieAllowed": true,
  "hasEnded": true,
  "rounds": [
    {
      "scores": [
        [],
        []
      ],
      "fouls": [
        [],
        []
      ],
      "baskets": [
        "magenta",
        "blue"
      ],
      "hasEnded": true,
      "isConfirmed": true,
      "roundMaxLength": 60000,
      "runs": [
        {
          "startTime": 1611089282460,
          "endTime": 1611089285737
        }
      ]
    },
    {
      "scores": [
        [],
        []
      ],
      "fouls": [
        [],
        []
      ],
      "baskets": [
        "blue",
        "magenta"
      ],
      "hasEnded": true,
      "isConfirmed": true,
      "roundMaxLength": 60000,
      "runs": [
        {
          "startTime": 1611089287011,
          "endTime": 1611089287475
        }
      ]
    },
    {
      "scores": [
        [],
        [
          {
            "time": 1611089289259,
            "isValid": true
          }
        ]
      ],
      "fouls": [
        [],
        []
      ],
      "baskets": [
        "magenta",
        "blue"
      ],
      "hasEnded": true,
      "isConfirmed": true,
      "roundMaxLength": 60000,
      "runs": [
        {
          "startTime": 1611089288007,
          "endTime": 1611089290247
        }
      ]
    }
  ]
}